iliascw/Configuration.py
iliascw/ConfigurationStrings.py
iliascw/CourseWatcher.py
iliascw/IliasConfig.py
iliascw/Result.py
iliascw/__init__.py
iliascw-0.2.0.dist-info/COPYING
iliascw-0.2.0.dist-info/METADATA
iliascw-0.2.0.dist-info/WHEEL
iliascw-0.2.0.dist-info/top_level.txt
iliascw-0.2.0.dist-info/RECORD
