Metadata-Version: 2.1
Name: iliascw
Version: 0.2.0
Summary: Library to check if courses are available.
Home-page: https://gitlab.com/dann-merlin/ilias-course-watcher
Author: Merlin Sievers
Author-email: merlin.sievers@posteo.net
Classifier: License :: OSI Approved :: GNU Affero General Public License v3
Classifier: Programming Language :: Python :: 3
Classifier: Programming Language :: Python :: 3.10
License-File: COPYING
Requires-Dist: beautifulsoup4 (==4.12.0)
Requires-Dist: certifi (==2022.12.7)
Requires-Dist: charset-normalizer (==3.1.0)
Requires-Dist: idna (==3.4)
Requires-Dist: pydantic (==1.10.7)
Requires-Dist: requests (==2.28.2)
Requires-Dist: soupsieve (==2.4)
Requires-Dist: typing-extensions (==4.5.0)
Requires-Dist: urllib3 (==1.26.15)
